kitsupy/__init__.py
kitsupy/kitsupy.py
kitsupy-1.1.dist-info/LICENSE
kitsupy-1.1.dist-info/METADATA
kitsupy-1.1.dist-info/WHEEL
kitsupy-1.1.dist-info/top_level.txt
kitsupy-1.1.dist-info/RECORD
