Metadata-Version: 2.1
Name: kitsupy
Version: 1.1
Summary: A simple api wrapper for the kitsu api written in python
Home-page: https://github.com/MetaStag/Pykitsu
Author: MetaStag
Author-email: thegreek132@gmail.com
License: UNKNOWN
Keywords: python,api-wrapper,kitsu,anime
Platform: UNKNOWN
Classifier: License :: OSI Approved :: MIT License
Classifier: Programming Language :: Python :: 3
Classifier: Programming Language :: Python :: 3.7
Classifier: Programming Language :: Python :: 3.8
Classifier: Programming Language :: Python :: 3.9
Classifier: Intended Audience :: Developers
License-File: LICENSE
Requires-Dist: requests
